media/__init__.py
media/package_data.dat
py_media-0.0.1.data/data/my_data/data_file
py_media-0.0.1.dist-info/LICENSE.txt
py_media-0.0.1.dist-info/METADATA
py_media-0.0.1.dist-info/WHEEL
py_media-0.0.1.dist-info/entry_points.txt
py_media-0.0.1.dist-info/top_level.txt
py_media-0.0.1.dist-info/RECORD
