Metadata-Version: 2.1
Name: py-media
Version: 0.0.1
Summary: Media
Home-page: https://github.com/shogoorg/py-media
Author: Shogo
Author-email: shogo@example.com
License: UNKNOWN
Project-URL: Bug Reports, https://github.com/shogoorg/py-media/issues
Project-URL: Source, https://github.com/shogoorg/py-media/
Keywords: media ethereum ipfs
Platform: UNKNOWN
Classifier: Development Status :: 3 - Alpha
Classifier: Intended Audience :: Developers
Classifier: Topic :: Software Development :: Build Tools
Classifier: License :: OSI Approved :: MIT License
Classifier: Programming Language :: Python :: 3
Classifier: Programming Language :: Python :: 3.6
Requires-Python: >=3.6, <4
Requires-Dist: peppercorn
Provides-Extra: dev
Requires-Dist: check-manifest ; extra == 'dev'
Provides-Extra: test
Requires-Dist: coverage ; extra == 'test'
